doti/__init__.py
doti/doti.py
doti/helpers/__init__.py
doti/helpers/boolean.py
doti/helpers/metadata.py
doti/helpers/path.py
doti/helpers/system.py
doti/options/__init__.py
doti/options/args.py
doti/options/config.py
doti/options/settings.py
doti/stow/__init__.py
doti/stow/print_results.py
doti/stow/stow.py
doti/stow/stow_exists.py
doti-0.4.0.dist-info/METADATA
doti-0.4.0.dist-info/WHEEL
doti-0.4.0.dist-info/entry_points.txt
doti-0.4.0.dist-info/licenses/LICENSE
doti-0.4.0.dist-info/RECORD
