Metadata-Version: 2.3
Name: doti
Version: 0.4.0
Summary: Easily manage all your dotfiles across your devices
Project-URL: Homepage, https://github.com/alduraibi/doti
Project-URL: Bug Tracker, https://github.com/alduraibi/doti/issues
Author-email: Ghassan Alduraibi <doti@ghassan.dev>
License-Expression: GPL-3.0-only
License-File: LICENSE
Classifier: License :: OSI Approved :: GNU General Public License v3 (GPLv3)
Classifier: Operating System :: MacOS
Classifier: Operating System :: POSIX
Classifier: Programming Language :: Python :: 3
Classifier: Topic :: Utilities
Requires-Python: >=3.7
